[{"query":"俄军抵达乌克兰作战前线","display_query":"俄军抵达乌克兰作战前线"},{"query":"裸背拍照道歉","display_query":"杭州小区裸背拍照网红道歉"},{"query":"画江湖之不良人","display_query":"《画江湖之不良人》第五季更新"},{"query":"南派三叔","display_query":"南派三叔 1547 万股权被冻结"},{"query":"乌克兰","display_query":"乌克兰放弃加入任何军事联盟"},{"query":"i 茅台","display_query":"i 茅台成为 App Store 免费榜第一"},{"query":"高铁列车长确诊","display_query":"一高铁列车长确诊"},{"query":"太空出差","display_query":"太空出差三人组开始收拾"},{"query":"海贼王","display_query":"海贼王 1045 话情报"},{"query":"俄罗斯断供","display_query":"若欧洲不以卢布结算将断供天然气"}]