[{"query":"莫斯科号巡洋舰","display_query":"莫斯科号巡洋舰已沉没"},{"query":"违法失德人员 直播发声","display_query":"严禁违法失德人员直播发声出镜"},{"query":"iPhoneSE3 日本 卖爆","display_query":"iPhone SE 3 日本卖爆"},{"query":"高校毕业生数量","display_query":"高校毕业生预计有 1076 万人"},{"query":"疫苗龙头智飞生物","display_query":"2000 亿市值疫苗龙头闪崩"},{"query":"卢伟冰 K50 样张","display_query":"卢伟冰发布 K50 样张遭吐槽"},{"query":"俄罗斯 匕首 高超声速导弹","display_query":"俄再使用「匕首」高超声速导弹"},{"query":"豆瓣发布处罚公告","display_query":"豆瓣发布「饭圈」乱象治理的处罚公告"},{"query":"诺亚之心","display_query":"诺亚之心手游上线"},{"query":"教师资格证笔试成绩公布","display_query":"2022 上半年教师资格证笔试成绩公布"}]