[{"query":"卢伟冰 K50 样张","display_query":"卢伟冰发布 K50 样张遭吐槽"},{"query":"封控小区 阳性感染者","display_query":"上海回应封控小区为何现阳性感染者"},{"query":"iPhoneSE3 日本 卖爆","display_query":"iPhone SE 3 日本卖爆"},{"query":"鸿蒙3.0将发布","display_query":"曝鸿蒙 3.0 将于 9 月发布"},{"query":"顿巴斯大战","display_query":"俄乌或迎来顿巴斯大战"},{"query":"康师傅 老坛酸菜面 重新上架","display_query":"康师傅回应老坛酸菜面重新上架"},{"query":"违法失德人员 直播发声","display_query":"严禁违法失德人员直播发声出镜"},{"query":"豆瓣发布处罚公告","display_query":"豆瓣发布「饭圈」乱象治理的处罚公告"},{"query":"高校毕业生数量","display_query":"高校毕业生预计有 1076 万人"},{"query":"上海发布疫情期间电商经营合规警示","display_query":"上海市监局发布疫情期间电商经营合规警示"}]