[{"query":"uzi","display_query":"Uzi 首胜"},{"query":"吉林疫情","display_query":"吉林新增 895 例本土确诊"},{"query":"凡人修仙传","display_query":"《凡人修仙传》动画更新"},{"query":"广东省公安厅副厅长被免职","display_query":"广东省公安厅副厅长被免职"},{"query":"奥密克戎 BA.2 变异株","display_query":"多地疫情涉奥密克戎 BA.2 变异株"},{"query":"北京冬残奥会奖牌","display_query":"北京冬残奥会中国 18 金"},{"query":"上海六院","display_query":"上海六院因疫情暂停临港院区相关医疗服务"},{"query":"深圳全市公交地铁停运","display_query":"深圳全市公交地铁停运"},{"query":"奥巴马","display_query":"奥巴马新冠检测呈阳性"},{"query":"张文宏","display_query":"张文宏称这波疫情是倒春寒"}]