[{"query":"绥化教育局回应","display_query":"绥化教育局回应开除学生"},{"query":"江苏人大主席 通奸","display_query":"江苏人大主席与人妻通奸被抓"},{"query":"本土感染者","display_query":"3 月以来本土感染者 49 万多例"},{"query":"小米MIUIGo","display_query":"小米 MIUI Go 曝光"},{"query":"吴尊友 新冠病毒变异规律","display_query":"吴尊友称没发现新冠病毒变异的规律性"},{"query":"iPhone 潜望式长焦","display_query":"iPhone 15 Pro 或引入潜望式长焦镜头"},{"query":"vivo X80","display_query":"vivo X80 系列宣布定档"},{"query":"上海男子囤菜","display_query":"上海男子囤菜赚百万被采取强制措施"},{"query":"王思聪微博账号被禁言","display_query":"王思聪微博账号被禁言"},{"query":"英特种部队 乌克兰","display_query":"英特种部队前往乌克兰教学"}]